scoobi/__init__.py
scoobi/cli.py
scoobi/config.py
scoobi/fitscubetofits.py
scoobi-0.0.1.8.dist-info/LICENSE
scoobi-0.0.1.8.dist-info/METADATA
scoobi-0.0.1.8.dist-info/WHEEL
scoobi-0.0.1.8.dist-info/entry_points.txt
scoobi-0.0.1.8.dist-info/top_level.txt
scoobi-0.0.1.8.dist-info/RECORD
