Metadata-Version: 2.1
Name: scoobi
Version: 0.0.1.8
Summary: Solar Conventionality-based Organizing Observation data ( SCOOBI )
Home-page: https://github.com/avialxee/scoobi
Author: Avinash Kumar
Author-email: avialxee@gmail.com
Project-URL: Bug Tracker, https://github.com/avialxee/scoobi/issues
Classifier: Programming Language :: Python :: 3
Classifier: Programming Language :: Python :: 3.7
Classifier: Programming Language :: Python :: 3.8
Classifier: Programming Language :: Python :: 3.9
Classifier: Programming Language :: Python :: 3.10
Classifier: License :: OSI Approved :: BSD License
Classifier: Intended Audience :: Science/Research
License-File: LICENSE
Requires-Dist: astropy
Requires-Dist: numpy
Requires-Dist: exifread
Provides-Extra: dev
Requires-Dist: pytest >=3.7 ; extra == 'dev'
